dips/AnchorPointVal.py
dips/AngleDataVal.py
dips/AnnotativeTools2DVal.py
dips/ApplicationManager.py
dips/ArrowToolEntityInfoRef.py
dips/ArrowToolEntityInfoVal.py
dips/AutomaticClusterAnalysisSettingsVal.py
dips/BuiltInDataDescriptors.py
dips/BuiltInDataFormatters.py
dips/CircularWindowVal.py
dips/ClusterWindowVal.py
dips/ColorSurrogateVal.py
dips/ConeToolEntityInfoRef.py
dips/ConeToolEntityInfoVal.py
dips/ConeVal.py
dips/ContourEntityVisibilityVal.py
dips/ContourOptionsVal.py
dips/CumulativeChartViewRef.py
dips/CumulativeChartViewVal.py
dips/CumulativePlotSettingsVal.py
dips/CurvedWindowVal.py
dips/CustomColumnCollectionVal.py
dips/CustomHistogramOptionsVal.py
dips/CustomRangeVal.py
dips/CustomRowRawDataVal.py
dips/DataDescriptorVal.py
dips/DataFilterRef.py
dips/DataFilterVal.py
dips/DataFormatterVal.py
dips/DataIdentifierVal.py
dips/DipsAPI_pb2.py
dips/DipsAPI_pb2_grpc.py
dips/DipsApp.py
dips/DiscontinuityDataVal.py
dips/EllipseToolEntityInfoRef.py
dips/EllipseToolEntityInfoVal.py
dips/FillFormatVal.py
dips/FoldEntityInfoRef.py
dips/FoldEntityInfoVal.py
dips/FoldEntityOptionsVal.py
dips/FoldEntityVisibilityRef.py
dips/FoldEntityVisibilityVal.py
dips/FoldWindowEntityInfoVal.py
dips/FoldWindowEntityVisibilityRef.py
dips/FoldWindowEntityVisibilityVal.py
dips/FreehandWindowVal.py
dips/FullDataFormatVal.py
dips/GlobalPlaneEntityVisibilityVal.py
dips/HistogramChartViewRef.py
dips/HistogramChartViewVal.py
dips/HistogramPlotSettingsVal.py
dips/IntersectionEntityVisibilityVal.py
dips/IntersectionOptionsVal.py
dips/IntervalVal.py
dips/JointFrequencyAnalysisSettingsVal.py
dips/JointFrequencyChartViewRef.py
dips/JointFrequencyChartViewVal.py
dips/JointSpacingAnalysisSettingsVal.py
dips/JointSpacingChartViewRef.py
dips/JointSpacingChartViewVal.py
dips/KinematicAnalysisEntityVisibilityVal.py
dips/KinematicAnalysisSettingsVal.py
dips/LatLongVal.py
dips/LengthDataVal.py
dips/LineFormatVal.py
dips/LineIntersectionCalculatorToolEntityInfoRef.py
dipsscripting-9.1.0.dist-info/licenses/License.txt
dipsscripting-9.1.0.dist-info/METADATA
dipsscripting-9.1.0.dist-info/WHEEL
dipsscripting-9.1.0.dist-info/top_level.txt
dipsscripting-9.1.0.dist-info/RECORD
