Metadata-Version: 2.4
Name: DipsScripting
Version: 9.1.0
Summary: Client library for interacting with Dips through python
Author: Rocscience
Project-URL: Homepage, https://www.rocscience.com/software/dips
Project-URL: Documentation, https://www.rocscience.com/help/dips/overview
Keywords: Rocscience,Dips,Scripting,RocScript,Geotechnical
Classifier: Programming Language :: Python :: 3
Classifier: License :: OSI Approved :: MIT License
Classifier: Topic :: Scientific/Engineering
Requires-Python: >=3.7
License-File: License.txt
Requires-Dist: grpcio
Requires-Dist: protobuf<6.0
Requires-Dist: pytest>=7.0.0
Requires-Dist: pytest-mock>=3.0.0
Dynamic: license-file
